README.md
setup.py
lps_maestro/__init__.c
lps_maestro/__init__.py
lps_maestro/authenticate.c
lps_maestro/authenticate.py
lps_maestro/castor.c
lps_maestro/castor.py
lps_maestro/constants.c
lps_maestro/constants.py
lps_maestro/task.c
lps_maestro/task.py
lps_maestro/utils.c
lps_maestro/utils.py
lps_maestro.egg-info/PKG-INFO
lps_maestro.egg-info/SOURCES.txt
lps_maestro.egg-info/dependency_links.txt
lps_maestro.egg-info/requires.txt
lps_maestro.egg-info/top_level.txt