Metadata-Version: 2.1
Name: lps-maestro
Version: 0.3.1
Summary: Command line interface for the LPS Cluster @ UFRJ.
Home-page: https://github.com/gabriel-milan/maestro
Author: Gabriel Gazola Milan
Author-email: gabriel.gazola@poli.ufrj.br
License: GPL-3.0
Keywords: cli,cluster,command-line interface,computer grid,lps,ufrj
Platform: UNKNOWN
Classifier: Development Status :: 4 - Beta
Classifier: Intended Audience :: Developers
Classifier: Topic :: Software Development :: Libraries :: Python Modules
Classifier: License :: OSI Approved :: GNU General Public License v3 (GPLv3)
Classifier: Programming Language :: Python :: 3
Classifier: Programming Language :: Python :: 3.4
Classifier: Programming Language :: Python :: 3.5
Classifier: Programming Language :: Python :: 3.6
Classifier: Programming Language :: Python :: 3.7
Classifier: Programming Language :: Python :: 3.8
